pyxui_async/__init__.py
pyxui_async/xui.py
pyxui_async/config_gen/__init__.py
pyxui_async/errors/__init__.py
pyxui_async/methods/__init__.py
pyxui_async/methods/base.py
pyxui_async/methods/clients.py
pyxui_async/methods/inbounds.py
pyxui_async/methods/login.py
pyxui_async-1.0.2.dist-info/LICENSE
pyxui_async-1.0.2.dist-info/METADATA
pyxui_async-1.0.2.dist-info/WHEEL
pyxui_async-1.0.2.dist-info/top_level.txt
pyxui_async-1.0.2.dist-info/RECORD
