Metadata-Version: 2.1
Name: pyxui-async
Version: 1.0.2
Summary: An application with python that allows you to modify your xui panel
Home-page: https://github.com/ARLIKIN/pyxui_async
Author: Staliox, ARLIKIN
License: MIT
Keywords: pyxui async,xui,xui python,xui panel
Classifier: Programming Language :: Python :: 3
Classifier: License :: OSI Approved :: MIT License
License-File: LICENSE
Requires-Dist: requests
